hello.py
foo_app_27216-0.1.0.dist-info/METADATA
foo_app_27216-0.1.0.dist-info/WHEEL
foo_app_27216-0.1.0.dist-info/top_level.txt
foo_app_27216-0.1.0.dist-info/RECORD
